[
  {
    "timestamp": "2025-07-13T11:40:03.048Z"
  },
  {
    "timestamp": "2025-07-13T11:48:53.827Z"
  },
  {
    "timestamp": "2025-07-13T12:25:33.985Z"
  },
  {
    "timestamp": "2025-07-13T13:03:49.844Z"
  },
  {
    "timestamp": "2025-07-13T13:38:36.151Z"
  },
  {
    "timestamp": "2025-07-13T13:51:12.371Z"
  },
  {
    "timestamp": "2025-07-13T14:12:05.087Z"
  },
  {
    "timestamp": "2025-07-13T14:32:37.606Z"
  },
  {
    "timestamp": "2025-07-13T14:49:17.045Z"
  },
  {
    "timestamp": "2025-07-13T15:12:57.200Z"
  },
  {
    "timestamp": "2025-07-13T15:31:43.405Z"
  },
  {
    "timestamp": "2025-07-13T15:49:00.571Z"
  },
  {
    "timestamp": "2025-07-13T16:15:37.914Z"
  },
  {
    "timestamp": "2025-07-13T16:44:56.190Z"
  },
  {
    "timestamp": "2025-07-13T16:55:31.442Z"
  },
  {
    "timestamp": "2025-07-13T17:11:27.885Z"
  },
  {
    "timestamp": "2025-07-13T17:31:11.905Z"
  },
  {
    "timestamp": "2025-07-13T17:50:16.974Z"
  },
  {
    "timestamp": "2025-07-13T18:18:02.511Z"
  },
  {
    "timestamp": "2025-07-13T18:46:39.196Z"
  },
  {
    "timestamp": "2025-07-13T19:10:45.307Z"
  },
  {
    "timestamp": "2025-07-13T19:25:26.242Z"
  },
  {
    "timestamp": "2025-07-13T19:35:46.717Z"
  },
  {
    "timestamp": "2025-07-13T19:48:10.161Z"
  },
  {
    "timestamp": "2025-07-13T20:14:13.399Z"
  },
  {
    "timestamp": "2025-07-13T20:33:01.523Z"
  },
  {
    "timestamp": "2025-07-13T20:49:37.020Z"
  },
  {
    "timestamp": "2025-07-13T21:12:15.600Z"
  },
  {
    "timestamp": "2025-07-13T21:29:24.089Z"
  },
  {
    "timestamp": "2025-07-13T21:40:53.837Z"
  },
  {
    "timestamp": "2025-07-13T21:48:32.192Z"
  },
  {
    "timestamp": "2025-07-13T22:13:06.353Z"
  },
  {
    "timestamp": "2025-07-13T22:34:58.921Z"
  },
  {
    "timestamp": "2025-07-13T22:51:01.550Z"
  },
  {
    "timestamp": "2025-07-13T23:14:04.348Z"
  },
  {
    "timestamp": "2025-07-13T23:32:38.670Z"
  },
  {
    "timestamp": "2025-07-13T23:50:43.546Z"
  },
  {
    "timestamp": "2025-07-14T01:12:16.906Z"
  },
  {
    "timestamp": "2025-07-14T03:12:20.728Z"
  },
  {
    "timestamp": "2025-07-14T04:10:17.996Z"
  },
  {
    "timestamp": "2025-07-14T04:51:55.920Z"
  },
  {
    "timestamp": "2025-07-14T05:20:26.321Z"
  },
  {
    "timestamp": "2025-07-14T05:47:39.619Z"
  },
  {
    "timestamp": "2025-07-14T06:22:34.711Z"
  },
  {
    "timestamp": "2025-07-14T06:53:45.713Z"
  },
  {
    "timestamp": "2025-07-14T07:18:46.391Z"
  },
  {
    "timestamp": "2025-07-14T07:42:36.193Z"
  },
  {
    "timestamp": "2025-07-14T07:52:21.189Z"
  },
  {
    "timestamp": "2025-07-14T08:21:05.521Z"
  },
  {
    "timestamp": "2025-07-14T08:53:09.576Z"
  },
  {
    "timestamp": "2025-07-14T09:21:40.688Z"
  },
  {
    "timestamp": "2025-07-14T09:47:35.709Z"
  },
  {
    "timestamp": "2025-07-14T10:15:59.493Z"
  },
  {
    "timestamp": "2025-07-14T10:46:51.107Z"
  },
  {
    "timestamp": "2025-07-14T11:12:58.220Z"
  },
  {
    "timestamp": "2025-07-14T11:30:03.043Z"
  },
  {
    "timestamp": "2025-07-14T11:42:34.300Z"
  },
  {
    "timestamp": "2025-07-14T11:50:33.253Z"
  },
  {
    "timestamp": "2025-07-14T12:29:03.985Z"
  },
  {
    "timestamp": "2025-07-14T13:11:10.249Z"
  },
  {
    "timestamp": "2025-07-14T13:48:28.787Z"
  },
  {
    "timestamp": "2025-07-14T14:15:10.485Z"
  },
  {
    "timestamp": "2025-07-14T14:41:19.609Z"
  },
  {
    "timestamp": "2025-07-14T14:54:39.105Z"
  },
  {
    "timestamp": "2025-07-14T15:15:34.992Z"
  },
  {
    "timestamp": "2025-07-14T15:42:58.646Z"
  },
  {
    "timestamp": "2025-07-14T15:54:08.053Z"
  },
  {
    "timestamp": "2025-07-14T16:18:18.426Z"
  },
  {
    "timestamp": "2025-07-14T16:49:22.813Z"
  },
  {
    "timestamp": "2025-07-14T17:14:25.797Z"
  },
  {
    "timestamp": "2025-07-14T17:36:54.366Z"
  },
  {
    "timestamp": "2025-07-14T17:51:42.966Z"
  },
  {
    "timestamp": "2025-07-14T18:21:04.799Z"
  },
  {
    "timestamp": "2025-07-14T18:52:47.364Z"
  },
  {
    "timestamp": "2025-07-14T19:12:00.232Z"
  },
  {
    "timestamp": "2025-07-14T19:28:28.461Z"
  },
  {
    "timestamp": "2025-07-14T19:39:53.281Z"
  },
  {
    "timestamp": "2025-07-14T19:48:03.076Z"
  },
  {
    "timestamp": "2025-07-14T20:16:12.961Z"
  },
  {
    "timestamp": "2025-07-14T20:42:30.099Z"
  },
  {
    "timestamp": "2025-07-14T20:52:58.182Z"
  },
  {
    "timestamp": "2025-07-14T21:13:34.334Z"
  },
  {
    "timestamp": "2025-07-14T21:31:46.379Z"
  },
  {
    "timestamp": "2025-07-14T21:48:54.119Z"
  },
  {
    "timestamp": "2025-07-14T22:13:45.853Z"
  },
  {
    "timestamp": "2025-07-14T22:38:11.143Z"
  },
  {
    "timestamp": "2025-07-14T22:53:17.790Z"
  },
  {
    "timestamp": "2025-07-14T23:13:57.700Z"
  },
  {
    "timestamp": "2025-07-14T23:31:04.459Z"
  },
  {
    "timestamp": "2025-07-14T23:49:29.644Z"
  },
  {
    "timestamp": "2025-07-15T01:11:59.527Z"
  },
  {
    "timestamp": "2025-07-15T03:08:45.254Z"
  },
  {
    "timestamp": "2025-07-15T04:06:43.207Z"
  },
  {
    "timestamp": "2025-07-15T04:50:55.714Z"
  },
  {
    "timestamp": "2025-07-15T05:19:46.459Z"
  },
  {
    "timestamp": "2025-07-15T05:46:46.772Z"
  },
  {
    "timestamp": "2025-07-15T06:22:06.980Z"
  },
  {
    "timestamp": "2025-07-15T06:52:53.432Z"
  },
  {
    "timestamp": "2025-07-15T07:17:16.476Z"
  },
  {
    "timestamp": "2025-07-15T07:41:47.174Z"
  }
]